{"type":"object","required":["appUserId"],"x-tags":["models"],"properties":{"organizationId":{"type":"string"},"firstName":{"type":"string"},"lastName":{"type":"string"},"userToken":{"type":"string"},"password":{"type":"string"},"permissions":{"type":"array","items":{"type":"string","enum":["mobile","console"]}},"roles":{"type":"array","items":{"type":"string"}},"groups":{"type":"array","items":{"type":"string"}},"propertiesMap":{"type":"array","items":{"type":"string"}},"appUserId":{"type":"string"},"email":{"type":"string"},"contacts":{"type":"object"}}}